{
    "data": {
        "trainerType": "Miner",
        "minLevel": 20,
        "maxLevel": 40,
        "minPartyPokemon": 1,
        "maxPartyPokemon": 6,
        "winnings": 32
    },
    "pokemon": [
        {
            "name": "Roggenrola"
        },
        {
            "name": "Roggenrola"
        },
        {
            "name": "Boldore"
        },
        {
            "name": "Graveler"
        },
        {
            "name": "Rhyhorn"
        },
        {
            "name": "Dwebble"
        },
        {
            "name": "Geodude"
        },
        {
            "name": "Geodude"
        },
        {
            "name": "Cranidos"
        },
        {
            "name": "Shieldon"
        },
        {
            "name": "Cranidos"
        },
        {
            "name": "Shieldon"
        },
        {
            "name": "Aron"
        },
        {
            "name": "Onix"
        },
        {
            "name": "Onix"
        },
        {
            "name": "Larvitar"
        },
        {
            "name": "Pupitar"
        },
        {
            "name": "Rampardos"
        },
        {
            "name": "Bastiodon"
        },
        {
            "name": "Probopass"
        },
        {
            "name": "Gigalith"
        },
        {
            "name": "Tyrunt"
        },
        {
            "name": "Tyrunt"
        },
        {
            "name": "Tyrantrum"
        },
        {
            "name": "Amaura"
        },
        {
            "name": "Amaura"
        },
        {
            "name": "Aurorus"
        },
        {
            "name": "Carbink"
        },
        {
            "name": "Carbink"
        },
        {
            "name": "Rolycoly"
        },
        {
            "name": "Rolycoly"
        },
        {
            "name": "Carkol"
        },
        {
            "name": "Coalossal"
        },
        {
            "name": "Diancie"
        }
    ],
    "names": [
        {
            "name": "Mac"
        },
        {
            "name": "Duggy"
        },
        {
            "name": "Bruce"
        },
        {
            "name": "Rocky"
        },
        {
            "name": "Benjamin Boulder"
        },
        {
            "name": "Gravelly Pete"
        },
        {
            "name": "Jimmy the Digger"
        },
        {
            "name": "Louis"
        },
        {
            "name": "Johanne"
        },
        {
            "name": "Haruto"
        },
        {
            "name": "Rui"
        },
        {
            "name": "Pierre"
        }
    ],
    "chat": [
        {
            "opening": "My Rock-type Pokémon are super tough!",
            "win": "Told you they were tough!",
            "lose": "Not as tough as I thought..."
        },
        {
            "opening": "I train my Rock types to stand up to anything.",
            "win": "They sure stood up to yours!",
            "lose": "Yours stood up a bit taller!"
        },
        {
            "opening": "Think you can beat a Rock-type Trainer, eh?",
            "win": "Not yet you can't! Keep training.",
            "lose": "I guess you can..."
        },
        {
            "opening": "Give me a Rock type over an Electric type any day!",
            "win": "My rockies are the best!",
            "lose": "Hmm. Well, you can't win 'em all..."
        },
        {
            "opening": "My Rock-type Pokémon are not sissies, like most others.",
            "win": "Nice try, but I warned you.",
            "lose": "I'm the sissy. My poor Pokémon!"
        }
    ]
}
