{
    "data": {
        "trainerType": "Pirate",
        "minLevel": 25,
        "maxLevel": 45,
        "minPartyPokemon": 2,
        "maxPartyPokemon": 4,
        "winnings": 48
    },
    "pokemon": [
        {
            "name": "Carvanha"
        },
        {
            "name": "Sharpedo"
        },
        {
            "name": "Wingull"
        },
        {
            "name": "Pelipper"
        },
        {
            "name": "Tentacool"
        },
        {
            "name": "Tentacruel"
        },
        {
            "name": "Wailmer"
        },
		{
			"name": "Wailord"
		}
    ],
    "names": [
        {
            "name": "Captain BlockBeard"
        },
        {
            "name": "Captain Crook"
        },
        {
            "name": "Captain Crawdaunt"
        },
        {
            "name": "Captain Morgan"
        },
        {
            "name": "Long John Silver"
        },
		{
            "name": "Pirate grunt"
        },
        {
            "name": "Pegleg Pete"
        },
        {
            "name": "Cannonball"
        },
        {
            "name": "Calico Jack"
        },
        {
            "name": "Scuz"
        }
    ],
	"chat": [
        {
            "opening": "Arrgghh!!",
            "win": "Zeit für dich über die Planke zu gehen!",
            "lose": "Sieht so aus als ob ich das Deck schrubben muss..."
        },
        {
            "opening": "Zeit um den Schatz zu verteidigen.",
            "win": "Sieht so aus als ob der Schatz mein is!",
            "lose": "Argh, du hast mich besiegt. Der Schatz gehört dir"
        }
    ]
}
